./.gitignore
./CHANGES.md
./COPYING
./FLAKE8
./MYPY
./Makefile
./PKG-INFO
./PYLINT
./README.md
./RERUN
./TOOLS.md
./adl_glc_ratios.py
./adl_grt_ratios.py
./all-tester
./arl-retlat.json
./bdw-cpuinfo
./bdw_client_ratios.py
./bdx_server_ratios.py
./cleanlogs
./clx_server_ratios.py
./counterdiff.py
./cpumap.sh
./cputop
./cputop.py
./csv_formats.py
./dummyarith.py
./ehl_ratios.py
./event-rmap.py
./event-translate.py
./event_download
./event_download.py
./fake-perf.py
./frequency.py
./gen-dot.py
./gen_level.py
./genretlat
./genretlat.py
./gnr-retlat.json
./gnr_server_ratios.py
./hsw_client_ratios.py
./hsx_server_ratios.py
./icl_client_ratios.py
./icx_server_ratios.py
./interval-merge
./interval-merge.py
./interval-normalize
./interval-normalize.py
./interval-plot
./interval-plot.py
./ivb_client_ratios.py
./ivb_server_ratios.py
./jkt_server_ratios.py
./knl_ratios.py
./latego.py
./linux_metrics.py
./list-events.py
./listutils.py
./lnl-retlat.json
./lnl_lnc_ratios.py
./lnl_skt_ratios.py
./metrics.py
./msr
./msr.py
./mtl-retlat.json
./mtl_cmt_ratios.py
./mtl_rwc_ratios.py
./node.py
./objutils.py
./oc-all-events
./ocperf
./ocperf.py
./other-tester
./parallel-tester
./pci.py
./perf_metrics.py
./plot-normalized.py
./pmudef.py
./pmumon.py
./power_metrics.py
./pyproject.toml
./requirements.txt
./simple_ratios.py
./skl_client_ratios.py
./skx_server_ratios.py
./slm_ratios.py
./snb_client_ratios.py
./spr_max_server_ratios.py
./spr_server_ratios.py
./srf_ratios.py
./test-uncore.json
./tester
./tl-barplot.py
./tl-serve
./tl-serve.py
./tl-tester
./tl-xlsx.py
./tl_cpu.py
./tl_io.py
./tl_output.py
./tl_stat.py
./tl_uval.py
./tldata.py
./toplev
./toplev.ico
./toplev.man
./toplev.py
./topology
./tsx_metrics.py
./utilized.py
./wl-bottlenecks
./.github/workflows/codeql-analysis.yml
./.github/workflows/jevents.yml
./.github/workflows/python-old.yml
./.github/workflows/python.yml
./.github/workflows/workflow.yml
./jevents/Makefile
./jevents/README.md
./jevents/cache.c
./jevents/cpustr.c
pmu_tools-2026.1.8.0.dist-info/METADATA
pmu_tools-2026.1.8.0.dist-info/WHEEL
pmu_tools-2026.1.8.0.dist-info/entry_points.txt
pmu_tools-2026.1.8.0.dist-info/licenses/COPYING
pmu_tools-2026.1.8.0.dist-info/RECORD
