Metadata-Version: 2.4
Name: pmu_tools
Version: 2026.1.8.0
Summary: pmu tools is a collection of tools and libraries for profile collection and performance analysis on Intel CPUs on top of Linux perf. This uses performance counters in the CPU.
Project-URL: Homepage, https://github.com/andikleen/pmu-tools/
Project-URL: Issues, https://github.com/andikleen/pmu-tools/issues
Author-email: Andi Kleen <pmu-tools@halobates.de>
License-Expression: GPL-2.0-only
License-File: COPYING
Classifier: License :: OSI Approved :: GNU General Public License v2 (GPLv2)
Classifier: Operating System :: OS Independent
Classifier: Programming Language :: Python :: 3
Requires-Python: >=3.9
